{
  "minicart.v2#store-theme": {
    "props": {
      "MinicartIcon": "icon-cart#minicart-icon"
    },
    "children": ["minicart-base-content#store-theme"]
  },
  "icon-cart#minicart-icon": {
    "props": {
      "size": 24
    }
  },
  "minicart-base-content#store-theme": {
    "blocks": ["minicart-empty-state"],
    "children": ["minicart-product-list", "flex-layout.row#minicart-footer"]
  },
  "flex-layout.row#minicart-footer": {
    "props": {
      "blockClass": "minicart-footer"
    },
    "children": ["flex-layout.col#minicart-footer"]
  },
  "flex-layout.col#minicart-footer": {
    "children": [
      "minicart-summary#summary",
      "minicart-checkout-button"
    ]
  },
  "minicart-summary#summary": {
    "blocks": [
      "checkout-summary.compact#minicart"
    ]
  },
  "checkout-summary.compact#minicart": {
    "children": [
      "summary-coupon",
      "summary-totalizers"
    ]
  }
}
